ms_recognizers_date_time/__init__.py
ms_recognizers_date_time/date_time/__init__.py
ms_recognizers_date_time/date_time/abstract_year_extractor.py
ms_recognizers_date_time/date_time/base_configs.py
ms_recognizers_date_time/date_time/base_date.py
ms_recognizers_date_time/date_time/base_dateperiod.py
ms_recognizers_date_time/date_time/base_datetime.py
ms_recognizers_date_time/date_time/base_datetimeperiod.py
ms_recognizers_date_time/date_time/base_duration.py
ms_recognizers_date_time/date_time/base_holiday.py
ms_recognizers_date_time/date_time/base_merged.py
ms_recognizers_date_time/date_time/base_set.py
ms_recognizers_date_time/date_time/base_time.py
ms_recognizers_date_time/date_time/base_timeperiod.py
ms_recognizers_date_time/date_time/base_timezone.py
ms_recognizers_date_time/date_time/constants.py
ms_recognizers_date_time/date_time/date_extractor.py
ms_recognizers_date_time/date_time/date_time_extractor.py
ms_recognizers_date_time/date_time/date_time_recognizer.py
ms_recognizers_date_time/date_time/datetime_list_extractor.py
ms_recognizers_date_time/date_time/datetime_zone_extractor.py
ms_recognizers_date_time/date_time/extractors.py
ms_recognizers_date_time/date_time/models.py
ms_recognizers_date_time/date_time/parsers.py
ms_recognizers_date_time/date_time/utilities.py
ms_recognizers_date_time/date_time/chinese/__init__.py
ms_recognizers_date_time/date_time/chinese/base_date_time_extractor.py
ms_recognizers_date_time/date_time/chinese/date_extractor.py
ms_recognizers_date_time/date_time/chinese/date_extractor_config.py
ms_recognizers_date_time/date_time/chinese/date_parser.py
ms_recognizers_date_time/date_time/chinese/date_parser_config.py
ms_recognizers_date_time/date_time/chinese/dateperiod_extractor.py
ms_recognizers_date_time/date_time/chinese/dateperiod_extractor_config.py
ms_recognizers_date_time/date_time/chinese/dateperiod_parser.py
ms_recognizers_date_time/date_time/chinese/dateperiod_parser_config.py
ms_recognizers_text_date_time-1.0.0.1.dist-info/METADATA
ms_recognizers_text_date_time-1.0.0.1.dist-info/WHEEL
ms_recognizers_text_date_time-1.0.0.1.dist-info/top_level.txt
ms_recognizers_text_date_time-1.0.0.1.dist-info/RECORD
